cyclonedds/_idlpy.cpython-310-darwin.so
cyclonedds/internal.py
cyclonedds/domain.py
cyclonedds/qos.py
cyclonedds/util.py
cyclonedds/pub.py
cyclonedds/__init__.py
cyclonedds/core.py
cyclonedds/dynamic.py
cyclonedds/__idlc__.py
cyclonedds/sub.py
cyclonedds/topic.py
cyclonedds/py.typed
cyclonedds/builtin.py
cyclonedds/builtin_types.py
cyclonedds/__library__.py
cyclonedds/_clayer.cpython-310-darwin.so
cyclonedds/idl/_type_helper.py
cyclonedds/idl/_main.py
cyclonedds/idl/_support.py
cyclonedds/idl/_xt_builder.py
cyclonedds/idl/__init__.py
cyclonedds/idl/types.py
cyclonedds/idl/_machinery.py
cyclonedds/idl/mypy_plugin.py
cyclonedds/idl/_builder.py
cyclonedds/idl/py.typed
cyclonedds/idl/_type_normalize.py
cyclonedds/idl/annotations.py
cyclonedds/idl/_typesupport/__init__.py
cyclonedds/idl/_typesupport/DDS/__init__.py
cyclonedds/idl/_typesupport/DDS/XTypes/_ddsi_xt_typemap.py
cyclonedds/idl/_typesupport/DDS/XTypes/_ddsi_xt_type_object.py
cyclonedds/idl/_typesupport/DDS/XTypes/__init__.py
cyclonedds/tools/__init__.py
cyclonedds/tools/wheel_idlc/__init__.py
cyclonedds/tools/ddsls/__init__.py
cyclonedds/tools/ddsls/__main__.py
cyclonedds/tools/cli/qosformat.py
cyclonedds/tools/cli/idl.py
cyclonedds/tools/cli/pub.py
cyclonedds/tools/cli/__init__.py
cyclonedds/tools/cli/ls.py
cyclonedds/tools/cli/common.py
cyclonedds/tools/cli/utils.py
cyclonedds/tools/cli/ps.py
cyclonedds/tools/cli/sub.py
cyclonedds/tools/cli/settings.py
cyclonedds/tools/cli/ddsperf.py
cyclonedds/tools/cli/main.py
cyclonedds/tools/cli/typeof.py
cyclonedds/tools/cli/layout/subscribe.py
cyclonedds/tools/cli/layout/__init__.py
cyclonedds/tools/cli/layout/barchart.py
cyclonedds/tools/cli/layout/pong.py
cyclonedds/tools/cli/layout/app.py
cyclonedds/tools/cli/layout/publish.py
cyclonedds/tools/cli/layout/ping.py
cyclonedds/tools/cli/discovery/type_discoverables.py
cyclonedds/tools/cli/discovery/__init__.py
cyclonedds/tools/cli/discovery/ls_discoverables.py
cyclonedds_nightly-2025.11.12.dist-info/RECORD
cyclonedds_nightly-2025.11.12.dist-info/WHEEL
cyclonedds_nightly-2025.11.12.dist-info/entry_points.txt
cyclonedds_nightly-2025.11.12.dist-info/top_level.txt
cyclonedds_nightly-2025.11.12.dist-info/METADATA
cyclonedds_nightly-2025.11.12.dist-info/licenses/LICENSE
