Metadata-Version: 2.4
Name: cyclonedds-nightly
Version: 2025.11.12
Summary: Eclipse Cyclone DDS Python binding
Home-page: https://cyclonedds.io
Author: Eclipse Cyclone DDS Committers
Maintainer: Thijs Miedema
Maintainer-email: thijs.miedema@zettascale.tech
License: EPL-2.0, BSD-3-Clause
Project-URL: Documentation, https://cyclonedds.io/docs
Project-URL: Source Code, https://github.com/eclipse-cyclonedds/cyclonedds-python
Project-URL: Bug Tracker, https://github.com/eclipse-cyclonedds/cyclonedds-python/issues
Keywords: eclipse,cyclone,dds,pub,sub,pubsub,iot,cyclonedds,cdr,omg,idl,middleware,ros
Platform: Windows
Platform: Linux
Platform: Mac OS-X
Platform: Unix
Classifier: Development Status :: 5 - Production/Stable
Classifier: Programming Language :: Python :: 3.10
Classifier: Programming Language :: Python :: 3.11
Classifier: Programming Language :: Python :: 3.12
Classifier: Programming Language :: Python :: 3.13
Classifier: Operating System :: OS Independent
Requires-Python: >=3.10
License-File: LICENSE
Requires-Dist: rich-click
Provides-Extra: dev
Requires-Dist: pytest>=6.2; extra == "dev"
Requires-Dist: pytest-asyncio; extra == "dev"
Requires-Dist: pytest-cov; extra == "dev"
Requires-Dist: pytest-mock; extra == "dev"
Requires-Dist: flake8; extra == "dev"
Requires-Dist: flake8-bugbear; extra == "dev"
Requires-Dist: twine; extra == "dev"
Provides-Extra: docs
Requires-Dist: Sphinx>=4.0.0; extra == "docs"
Requires-Dist: piccolo_theme>=0.12.0; extra == "docs"
Dynamic: author
Dynamic: classifier
Dynamic: description
Dynamic: description-content-type
Dynamic: home-page
Dynamic: keywords
Dynamic: license
Dynamic: license-file
Dynamic: maintainer
Dynamic: maintainer-email
Dynamic: platform
Dynamic: project-url
Dynamic: provides-extra
Dynamic: requires-dist
Dynamic: requires-python
Dynamic: summary
